model_manager_client/__init__.py
model_manager_client/async_client.py
model_manager_client/auth.py
model_manager_client/client.py
model_manager_client/exceptions.py
model_manager_client/sync_client.py
model_manager_client/enums/__init__.py
model_manager_client/enums/channel.py
model_manager_client/enums/invoke.py
model_manager_client/enums/providers.py
model_manager_client/generated/__init__.py
model_manager_client/generated/model_service_pb2.py
model_manager_client/generated/model_service_pb2_grpc.py
model_manager_client/schemas/__init__.py
model_manager_client/schemas/inputs.py
model_manager_client/schemas/outputs.py
model_manager_client-0.2.0.dist-info/METADATA
model_manager_client-0.2.0.dist-info/WHEEL
model_manager_client-0.2.0.dist-info/top_level.txt
model_manager_client-0.2.0.dist-info/RECORD
