Metadata-Version: 2.4
Name: model-manager-client
Version: 0.2.0
Summary: A Python SDK for interacting with the Model Manager gRPC service
Home-page: https://github.com/oscarou1992/model-manager-client
Author: Oscar Ou
Author-email: oscar.ou@tamaredge.ai
Classifier: Programming Language :: Python :: 3
Classifier: Programming Language :: Python :: 3.8
Classifier: Programming Language :: Python :: 3.9
Classifier: Programming Language :: Python :: 3.10
Classifier: Programming Language :: Python :: 3.11
Classifier: License :: OSI Approved :: MIT License
Classifier: Operating System :: OS Independent
Requires-Python: >=3.8
Requires-Dist: grpcio
Requires-Dist: grpcio-tools
Requires-Dist: pydantic
Requires-Dist: PyJWT
Requires-Dist: nest_asyncio
Requires-Dist: openai
Requires-Dist: google-genai
Dynamic: author
Dynamic: author-email
Dynamic: classifier
Dynamic: description
Dynamic: description-content-type
Dynamic: home-page
Dynamic: requires-dist
Dynamic: requires-python
Dynamic: summary
